smooth_import/__init__.py
smooth_import/importer.py
smooth_import-1.0.1.dist-info/METADATA
smooth_import-1.0.1.dist-info/WHEEL
smooth_import-1.0.1.dist-info/top_level.txt
smooth_import-1.0.1.dist-info/RECORD
